setup.py
pyramid_view_extras/__init__.py
pyramid_view_extras/example.py
pyramid_view_extras/tests.py
pyramid_views_extras.egg-info/PKG-INFO
pyramid_views_extras.egg-info/SOURCES.txt
pyramid_views_extras.egg-info/dependency_links.txt
pyramid_views_extras.egg-info/requires.txt
pyramid_views_extras.egg-info/top_level.txt